package com.google.android.gms.location.internal;

import android.app.PendingIntent;
import android.location.Location;
import android.os.Binder;
import android.os.IBinder;
import android.os.IInterface;
import android.os.Parcel;
import android.os.Parcelable.Creator;
import android.os.RemoteException;
import com.google.android.gms.internal.zzzp;
import com.google.android.gms.internal.zzzp.zza;
import com.google.android.gms.location.ActivityRecognitionResult;
import com.google.android.gms.location.GeofencingRequest;
import com.google.android.gms.location.LocationAvailability;
import com.google.android.gms.location.LocationRequest;
import com.google.android.gms.location.LocationSettingsRequest;
import com.google.android.gms.location.zza;
import com.google.android.gms.location.zzf;
import com.google.android.gms.location.zzn;
import com.google.android.gms.location.zzn.zza;
import com.google.android.gms.location.zzv;
import java.util.List;

public abstract interface zzk
  extends IInterface
{
  public abstract Location zzKo()
    throws RemoteException;
  
  public abstract void zza(long paramLong, boolean paramBoolean, PendingIntent paramPendingIntent)
    throws RemoteException;
  
  public abstract void zza(PendingIntent paramPendingIntent, zzzp paramzzzp)
    throws RemoteException;
  
  public abstract void zza(PendingIntent paramPendingIntent, zzj paramzzj, String paramString)
    throws RemoteException;
  
  public abstract void zza(Location paramLocation, int paramInt)
    throws RemoteException;
  
  public abstract void zza(GeofencingRequest paramGeofencingRequest, PendingIntent paramPendingIntent, zzj paramzzj)
    throws RemoteException;
  
  public abstract void zza(LocationRequest paramLocationRequest, PendingIntent paramPendingIntent)
    throws RemoteException;
  
  public abstract void zza(LocationRequest paramLocationRequest, zzn paramzzn)
    throws RemoteException;
  
  public abstract void zza(LocationRequest paramLocationRequest, zzn paramzzn, String paramString)
    throws RemoteException;
  
  public abstract void zza(LocationSettingsRequest paramLocationSettingsRequest, zzl paramzzl, String paramString)
    throws RemoteException;
  
  public abstract void zza(zzi paramzzi)
    throws RemoteException;
  
  public abstract void zza(zzj paramzzj, String paramString)
    throws RemoteException;
  
  public abstract void zza(zzo paramzzo, PendingIntent paramPendingIntent)
    throws RemoteException;
  
  public abstract void zza(zzo paramzzo, zzn paramzzn)
    throws RemoteException;
  
  public abstract void zza(zzq paramzzq)
    throws RemoteException;
  
  public abstract void zza(zza paramzza, PendingIntent paramPendingIntent, zzzp paramzzzp)
    throws RemoteException;
  
  public abstract void zza(zzf paramzzf, PendingIntent paramPendingIntent, zzzp paramzzzp)
    throws RemoteException;
  
  public abstract void zza(zzn paramzzn)
    throws RemoteException;
  
  public abstract void zza(zzv paramzzv, zzj paramzzj)
    throws RemoteException;
  
  public abstract void zza(List<zzt> paramList, PendingIntent paramPendingIntent, zzj paramzzj, String paramString)
    throws RemoteException;
  
  public abstract void zza(String[] paramArrayOfString, zzj paramzzj, String paramString)
    throws RemoteException;
  
  public abstract void zzaQ(boolean paramBoolean)
    throws RemoteException;
  
  public abstract void zzb(PendingIntent paramPendingIntent, zzzp paramzzzp)
    throws RemoteException;
  
  public abstract void zzc(PendingIntent paramPendingIntent)
    throws RemoteException;
  
  public abstract void zzc(PendingIntent paramPendingIntent, zzzp paramzzzp)
    throws RemoteException;
  
  public abstract void zzd(PendingIntent paramPendingIntent)
    throws RemoteException;
  
  public abstract void zzd(PendingIntent paramPendingIntent, zzzp paramzzzp)
    throws RemoteException;
  
  public abstract void zzd(Location paramLocation)
    throws RemoteException;
  
  public abstract void zzd(zzzp paramzzzp)
    throws RemoteException;
  
  public abstract void zze(PendingIntent paramPendingIntent, zzzp paramzzzp)
    throws RemoteException;
  
  public abstract ActivityRecognitionResult zzeR(String paramString)
    throws RemoteException;
  
  public abstract Location zzeS(String paramString)
    throws RemoteException;
  
  public abstract LocationAvailability zzeT(String paramString)
    throws RemoteException;
  
  public static abstract class zza
    extends Binder
    implements zzk
  {
    public static zzk zzfw(IBinder paramIBinder)
    {
      if (paramIBinder == null) {
        return null;
      }
      IInterface localIInterface = paramIBinder.queryLocalInterface("com.google.android.gms.location.internal.IGoogleLocationManagerService");
      if ((localIInterface != null) && ((localIInterface instanceof zzk))) {
        return (zzk)localIInterface;
      }
      return new zza(paramIBinder);
    }
    
    public boolean onTransact(int paramInt1, Parcel paramParcel1, Parcel paramParcel2, int paramInt2)
      throws RemoteException
    {
      boolean bool = false;
      Object localObject2;
      switch (paramInt1)
      {
      default: 
        return super.onTransact(paramInt1, paramParcel1, paramParcel2, paramInt2);
      case 1598968902: 
        paramParcel2.writeString("com.google.android.gms.location.internal.IGoogleLocationManagerService");
        return true;
      case 1: 
        paramParcel1.enforceInterface("com.google.android.gms.location.internal.IGoogleLocationManagerService");
        localObject2 = paramParcel1.createTypedArrayList(zzt.CREATOR);
        if (paramParcel1.readInt() != 0) {}
        for (localObject1 = (PendingIntent)PendingIntent.CREATOR.createFromParcel(paramParcel1);; localObject1 = null)
        {
          zza((List)localObject2, (PendingIntent)localObject1, zzj.zza.zzfv(paramParcel1.readStrongBinder()), paramParcel1.readString());
          paramParcel2.writeNoException();
          return true;
        }
      case 57: 
        paramParcel1.enforceInterface("com.google.android.gms.location.internal.IGoogleLocationManagerService");
        if (paramParcel1.readInt() != 0)
        {
          localObject1 = (GeofencingRequest)GeofencingRequest.CREATOR.createFromParcel(paramParcel1);
          if (paramParcel1.readInt() == 0) {
            break label448;
          }
        }
        for (localObject2 = (PendingIntent)PendingIntent.CREATOR.createFromParcel(paramParcel1);; localObject2 = null)
        {
          zza((GeofencingRequest)localObject1, (PendingIntent)localObject2, zzj.zza.zzfv(paramParcel1.readStrongBinder()));
          paramParcel2.writeNoException();
          return true;
          localObject1 = null;
          break;
        }
      case 2: 
        paramParcel1.enforceInterface("com.google.android.gms.location.internal.IGoogleLocationManagerService");
        if (paramParcel1.readInt() != 0) {}
        for (localObject1 = (PendingIntent)PendingIntent.CREATOR.createFromParcel(paramParcel1);; localObject1 = null)
        {
          zza((PendingIntent)localObject1, zzj.zza.zzfv(paramParcel1.readStrongBinder()), paramParcel1.readString());
          paramParcel2.writeNoException();
          return true;
        }
      case 3: 
        paramParcel1.enforceInterface("com.google.android.gms.location.internal.IGoogleLocationManagerService");
        zza(paramParcel1.createStringArray(), zzj.zza.zzfv(paramParcel1.readStrongBinder()), paramParcel1.readString());
        paramParcel2.writeNoException();
        return true;
      case 4: 
        paramParcel1.enforceInterface("com.google.android.gms.location.internal.IGoogleLocationManagerService");
        zza(zzj.zza.zzfv(paramParcel1.readStrongBinder()), paramParcel1.readString());
        paramParcel2.writeNoException();
        return true;
      case 74: 
        paramParcel1.enforceInterface("com.google.android.gms.location.internal.IGoogleLocationManagerService");
        if (paramParcel1.readInt() != 0) {}
        for (localObject1 = (zzv)zzv.CREATOR.createFromParcel(paramParcel1);; localObject1 = null)
        {
          zza((zzv)localObject1, zzj.zza.zzfv(paramParcel1.readStrongBinder()));
          paramParcel2.writeNoException();
          return true;
        }
      case 5: 
        paramParcel1.enforceInterface("com.google.android.gms.location.internal.IGoogleLocationManagerService");
        long l = paramParcel1.readLong();
        if (paramParcel1.readInt() != 0)
        {
          bool = true;
          if (paramParcel1.readInt() == 0) {
            break label683;
          }
        }
        for (paramParcel1 = (PendingIntent)PendingIntent.CREATOR.createFromParcel(paramParcel1);; paramParcel1 = null)
        {
          zza(l, bool, paramParcel1);
          paramParcel2.writeNoException();
          return true;
          bool = false;
          break;
        }
      case 70: 
        paramParcel1.enforceInterface("com.google.android.gms.location.internal.IGoogleLocationManagerService");
        if (paramParcel1.readInt() != 0)
        {
          localObject1 = (zza)zza.CREATOR.createFromParcel(paramParcel1);
          if (paramParcel1.readInt() == 0) {
            break label763;
          }
        }
        for (localObject2 = (PendingIntent)PendingIntent.CREATOR.createFromParcel(paramParcel1);; localObject2 = null)
        {
          zza((zza)localObject1, (PendingIntent)localObject2, zzzp.zza.zzcX(paramParcel1.readStrongBinder()));
          paramParcel2.writeNoException();
          return true;
          localObject1 = null;
          break;
        }
      case 71: 
        paramParcel1.enforceInterface("com.google.android.gms.location.internal.IGoogleLocationManagerService");
        zzd(zzzp.zza.zzcX(paramParcel1.readStrongBinder()));
        paramParcel2.writeNoException();
        return true;
      case 72: 
        paramParcel1.enforceInterface("com.google.android.gms.location.internal.IGoogleLocationManagerService");
        if (paramParcel1.readInt() != 0)
        {
          localObject1 = (zzf)zzf.CREATOR.createFromParcel(paramParcel1);
          if (paramParcel1.readInt() == 0) {
            break label867;
          }
        }
        for (localObject2 = (PendingIntent)PendingIntent.CREATOR.createFromParcel(paramParcel1);; localObject2 = null)
        {
          zza((zzf)localObject1, (PendingIntent)localObject2, zzzp.zza.zzcX(paramParcel1.readStrongBinder()));
          paramParcel2.writeNoException();
          return true;
          localObject1 = null;
          break;
        }
      case 73: 
        paramParcel1.enforceInterface("com.google.android.gms.location.internal.IGoogleLocationManagerService");
        if (paramParcel1.readInt() != 0) {}
        for (localObject1 = (PendingIntent)PendingIntent.CREATOR.createFromParcel(paramParcel1);; localObject1 = null)
        {
          zza((PendingIntent)localObject1, zzzp.zza.zzcX(paramParcel1.readStrongBinder()));
          paramParcel2.writeNoException();
          return true;
        }
      case 6: 
        paramParcel1.enforceInterface("com.google.android.gms.location.internal.IGoogleLocationManagerService");
        if (paramParcel1.readInt() != 0) {}
        for (paramParcel1 = (PendingIntent)PendingIntent.CREATOR.createFromParcel(paramParcel1);; paramParcel1 = null)
        {
          zzc(paramParcel1);
          paramParcel2.writeNoException();
          return true;
        }
      case 64: 
        paramParcel1.enforceInterface("com.google.android.gms.location.internal.IGoogleLocationManagerService");
        paramParcel1 = zzeR(paramParcel1.readString());
        paramParcel2.writeNoException();
        if (paramParcel1 != null)
        {
          paramParcel2.writeInt(1);
          paramParcel1.writeToParcel(paramParcel2, 1);
          return true;
        }
        paramParcel2.writeInt(0);
        return true;
      case 65: 
        paramParcel1.enforceInterface("com.google.android.gms.location.internal.IGoogleLocationManagerService");
        if (paramParcel1.readInt() != 0) {}
        for (localObject1 = (PendingIntent)PendingIntent.CREATOR.createFromParcel(paramParcel1);; localObject1 = null)
        {
          zzb((PendingIntent)localObject1, zzzp.zza.zzcX(paramParcel1.readStrongBinder()));
          paramParcel2.writeNoException();
          return true;
        }
      case 66: 
        paramParcel1.enforceInterface("com.google.android.gms.location.internal.IGoogleLocationManagerService");
        if (paramParcel1.readInt() != 0) {}
        for (localObject1 = (PendingIntent)PendingIntent.CREATOR.createFromParcel(paramParcel1);; localObject1 = null)
        {
          zzc((PendingIntent)localObject1, zzzp.zza.zzcX(paramParcel1.readStrongBinder()));
          paramParcel2.writeNoException();
          return true;
        }
      case 68: 
        paramParcel1.enforceInterface("com.google.android.gms.location.internal.IGoogleLocationManagerService");
        if (paramParcel1.readInt() != 0) {}
        for (localObject1 = (PendingIntent)PendingIntent.CREATOR.createFromParcel(paramParcel1);; localObject1 = null)
        {
          zzd((PendingIntent)localObject1, zzzp.zza.zzcX(paramParcel1.readStrongBinder()));
          paramParcel2.writeNoException();
          return true;
        }
      case 69: 
        paramParcel1.enforceInterface("com.google.android.gms.location.internal.IGoogleLocationManagerService");
        if (paramParcel1.readInt() != 0) {}
        for (localObject1 = (PendingIntent)PendingIntent.CREATOR.createFromParcel(paramParcel1);; localObject1 = null)
        {
          zze((PendingIntent)localObject1, zzzp.zza.zzcX(paramParcel1.readStrongBinder()));
          paramParcel2.writeNoException();
          return true;
        }
      case 7: 
        paramParcel1.enforceInterface("com.google.android.gms.location.internal.IGoogleLocationManagerService");
        paramParcel1 = zzKo();
        paramParcel2.writeNoException();
        if (paramParcel1 != null)
        {
          paramParcel2.writeInt(1);
          paramParcel1.writeToParcel(paramParcel2, 1);
          return true;
        }
        paramParcel2.writeInt(0);
        return true;
      case 8: 
        paramParcel1.enforceInterface("com.google.android.gms.location.internal.IGoogleLocationManagerService");
        if (paramParcel1.readInt() != 0) {}
        for (localObject1 = (LocationRequest)LocationRequest.CREATOR.createFromParcel(paramParcel1);; localObject1 = null)
        {
          zza((LocationRequest)localObject1, zzn.zza.zzfs(paramParcel1.readStrongBinder()));
          paramParcel2.writeNoException();
          return true;
        }
      case 20: 
        paramParcel1.enforceInterface("com.google.android.gms.location.internal.IGoogleLocationManagerService");
        if (paramParcel1.readInt() != 0) {}
        for (localObject1 = (LocationRequest)LocationRequest.CREATOR.createFromParcel(paramParcel1);; localObject1 = null)
        {
          zza((LocationRequest)localObject1, zzn.zza.zzfs(paramParcel1.readStrongBinder()), paramParcel1.readString());
          paramParcel2.writeNoException();
          return true;
        }
      case 9: 
        paramParcel1.enforceInterface("com.google.android.gms.location.internal.IGoogleLocationManagerService");
        if (paramParcel1.readInt() != 0)
        {
          localObject1 = (LocationRequest)LocationRequest.CREATOR.createFromParcel(paramParcel1);
          if (paramParcel1.readInt() == 0) {
            break label1431;
          }
        }
        for (paramParcel1 = (PendingIntent)PendingIntent.CREATOR.createFromParcel(paramParcel1);; paramParcel1 = null)
        {
          zza((LocationRequest)localObject1, paramParcel1);
          paramParcel2.writeNoException();
          return true;
          localObject1 = null;
          break;
        }
      case 52: 
        paramParcel1.enforceInterface("com.google.android.gms.location.internal.IGoogleLocationManagerService");
        if (paramParcel1.readInt() != 0) {}
        for (localObject1 = (zzo)zzo.CREATOR.createFromParcel(paramParcel1);; localObject1 = null)
        {
          zza((zzo)localObject1, zzn.zza.zzfs(paramParcel1.readStrongBinder()));
          paramParcel2.writeNoException();
          return true;
        }
      case 53: 
        paramParcel1.enforceInterface("com.google.android.gms.location.internal.IGoogleLocationManagerService");
        if (paramParcel1.readInt() != 0)
        {
          localObject1 = (zzo)zzo.CREATOR.createFromParcel(paramParcel1);
          if (paramParcel1.readInt() == 0) {
            break label1554;
          }
        }
        for (paramParcel1 = (PendingIntent)PendingIntent.CREATOR.createFromParcel(paramParcel1);; paramParcel1 = null)
        {
          zza((zzo)localObject1, paramParcel1);
          paramParcel2.writeNoException();
          return true;
          localObject1 = null;
          break;
        }
      case 10: 
        paramParcel1.enforceInterface("com.google.android.gms.location.internal.IGoogleLocationManagerService");
        zza(zzn.zza.zzfs(paramParcel1.readStrongBinder()));
        paramParcel2.writeNoException();
        return true;
      case 11: 
        paramParcel1.enforceInterface("com.google.android.gms.location.internal.IGoogleLocationManagerService");
        if (paramParcel1.readInt() != 0) {}
        for (paramParcel1 = (PendingIntent)PendingIntent.CREATOR.createFromParcel(paramParcel1);; paramParcel1 = null)
        {
          zzd(paramParcel1);
          paramParcel2.writeNoException();
          return true;
        }
      case 59: 
        paramParcel1.enforceInterface("com.google.android.gms.location.internal.IGoogleLocationManagerService");
        if (paramParcel1.readInt() != 0) {}
        for (paramParcel1 = (zzq)zzq.CREATOR.createFromParcel(paramParcel1);; paramParcel1 = null)
        {
          zza(paramParcel1);
          paramParcel2.writeNoException();
          return true;
        }
      case 12: 
        paramParcel1.enforceInterface("com.google.android.gms.location.internal.IGoogleLocationManagerService");
        if (paramParcel1.readInt() != 0) {
          bool = true;
        }
        zzaQ(bool);
        paramParcel2.writeNoException();
        return true;
      case 13: 
        paramParcel1.enforceInterface("com.google.android.gms.location.internal.IGoogleLocationManagerService");
        if (paramParcel1.readInt() != 0) {}
        for (paramParcel1 = (Location)Location.CREATOR.createFromParcel(paramParcel1);; paramParcel1 = null)
        {
          zzd(paramParcel1);
          paramParcel2.writeNoException();
          return true;
        }
      case 21: 
        paramParcel1.enforceInterface("com.google.android.gms.location.internal.IGoogleLocationManagerService");
        paramParcel1 = zzeS(paramParcel1.readString());
        paramParcel2.writeNoException();
        if (paramParcel1 != null)
        {
          paramParcel2.writeInt(1);
          paramParcel1.writeToParcel(paramParcel2, 1);
          return true;
        }
        paramParcel2.writeInt(0);
        return true;
      case 26: 
        paramParcel1.enforceInterface("com.google.android.gms.location.internal.IGoogleLocationManagerService");
        if (paramParcel1.readInt() != 0) {}
        for (localObject1 = (Location)Location.CREATOR.createFromParcel(paramParcel1);; localObject1 = null)
        {
          zza((Location)localObject1, paramParcel1.readInt());
          paramParcel2.writeNoException();
          return true;
        }
      case 67: 
        paramParcel1.enforceInterface("com.google.android.gms.location.internal.IGoogleLocationManagerService");
        zza(zzi.zza.zzfu(paramParcel1.readStrongBinder()));
        paramParcel2.writeNoException();
        return true;
      case 34: 
        label448:
        label683:
        label763:
        label867:
        label1431:
        label1554:
        paramParcel1.enforceInterface("com.google.android.gms.location.internal.IGoogleLocationManagerService");
        paramParcel1 = zzeT(paramParcel1.readString());
        paramParcel2.writeNoException();
        if (paramParcel1 != null)
        {
          paramParcel2.writeInt(1);
          paramParcel1.writeToParcel(paramParcel2, 1);
          return true;
        }
        paramParcel2.writeInt(0);
        return true;
      }
      paramParcel1.enforceInterface("com.google.android.gms.location.internal.IGoogleLocationManagerService");
      if (paramParcel1.readInt() != 0) {}
      for (Object localObject1 = (LocationSettingsRequest)LocationSettingsRequest.CREATOR.createFromParcel(paramParcel1);; localObject1 = null)
      {
        zza((LocationSettingsRequest)localObject1, zzl.zza.zzfx(paramParcel1.readStrongBinder()), paramParcel1.readString());
        paramParcel2.writeNoException();
        return true;
      }
    }
    
    private static class zza
      implements zzk
    {
      private IBinder zzrj;
      
      zza(IBinder paramIBinder)
      {
        this.zzrj = paramIBinder;
      }
      
      public IBinder asBinder()
      {
        return this.zzrj;
      }
      
      /* Error */
      public Location zzKo()
        throws RemoteException
      {
        // Byte code:
        //   0: invokestatic 31	android/os/Parcel:obtain	()Landroid/os/Parcel;
        //   3: astore_2
        //   4: invokestatic 31	android/os/Parcel:obtain	()Landroid/os/Parcel;
        //   7: astore_3
        //   8: aload_2
        //   9: ldc 33
        //   11: invokevirtual 37	android/os/Parcel:writeInterfaceToken	(Ljava/lang/String;)V
        //   14: aload_0
        //   15: getfield 18	com/google/android/gms/location/internal/zzk$zza$zza:zzrj	Landroid/os/IBinder;
        //   18: bipush 7
        //   20: aload_2
        //   21: aload_3
        //   22: iconst_0
        //   23: invokeinterface 43 5 0
        //   28: pop
        //   29: aload_3
        //   30: invokevirtual 46	android/os/Parcel:readException	()V
        //   33: aload_3
        //   34: invokevirtual 50	android/os/Parcel:readInt	()I
        //   37: ifeq +26 -> 63
        //   40: getstatic 56	android/location/Location:CREATOR	Landroid/os/Parcelable$Creator;
        //   43: aload_3
        //   44: invokeinterface 62 2 0
        //   49: checkcast 52	android/location/Location
        //   52: astore_1
        //   53: aload_3
        //   54: invokevirtual 65	android/os/Parcel:recycle	()V
        //   57: aload_2
        //   58: invokevirtual 65	android/os/Parcel:recycle	()V
        //   61: aload_1
        //   62: areturn
        //   63: aconst_null
        //   64: astore_1
        //   65: goto -12 -> 53
        //   68: astore_1
        //   69: aload_3
        //   70: invokevirtual 65	android/os/Parcel:recycle	()V
        //   73: aload_2
        //   74: invokevirtual 65	android/os/Parcel:recycle	()V
        //   77: aload_1
        //   78: athrow
        // Local variable table:
        //   start	length	slot	name	signature
        //   0	79	0	this	zza
        //   52	13	1	localLocation	Location
        //   68	10	1	localObject	Object
        //   3	71	2	localParcel1	Parcel
        //   7	63	3	localParcel2	Parcel
        // Exception table:
        //   from	to	target	type
        //   8	53	68	finally
      }
      
      /* Error */
      public void zza(long paramLong, boolean paramBoolean, PendingIntent paramPendingIntent)
        throws RemoteException
      {
        // Byte code:
        //   0: iconst_1
        //   1: istore 5
        //   3: invokestatic 31	android/os/Parcel:obtain	()Landroid/os/Parcel;
        //   6: astore 6
        //   8: invokestatic 31	android/os/Parcel:obtain	()Landroid/os/Parcel;
        //   11: astore 7
        //   13: aload 6
        //   15: ldc 33
        //   17: invokevirtual 37	android/os/Parcel:writeInterfaceToken	(Ljava/lang/String;)V
        //   20: aload 6
        //   22: lload_1
        //   23: invokevirtual 71	android/os/Parcel:writeLong	(J)V
        //   26: iload_3
        //   27: ifeq +61 -> 88
        //   30: aload 6
        //   32: iload 5
        //   34: invokevirtual 75	android/os/Parcel:writeInt	(I)V
        //   37: aload 4
        //   39: ifnull +55 -> 94
        //   42: aload 6
        //   44: iconst_1
        //   45: invokevirtual 75	android/os/Parcel:writeInt	(I)V
        //   48: aload 4
        //   50: aload 6
        //   52: iconst_0
        //   53: invokevirtual 81	android/app/PendingIntent:writeToParcel	(Landroid/os/Parcel;I)V
        //   56: aload_0
        //   57: getfield 18	com/google/android/gms/location/internal/zzk$zza$zza:zzrj	Landroid/os/IBinder;
        //   60: iconst_5
        //   61: aload 6
        //   63: aload 7
        //   65: iconst_0
        //   66: invokeinterface 43 5 0
        //   71: pop
        //   72: aload 7
        //   74: invokevirtual 46	android/os/Parcel:readException	()V
        //   77: aload 7
        //   79: invokevirtual 65	android/os/Parcel:recycle	()V
        //   82: aload 6
        //   84: invokevirtual 65	android/os/Parcel:recycle	()V
        //   87: return
        //   88: iconst_0
        //   89: istore 5
        //   91: goto -61 -> 30
        //   94: aload 6
        //   96: iconst_0
        //   97: invokevirtual 75	android/os/Parcel:writeInt	(I)V
        //   100: goto -44 -> 56
        //   103: astore 4
        //   105: aload 7
        //   107: invokevirtual 65	android/os/Parcel:recycle	()V
        //   110: aload 6
        //   112: invokevirtual 65	android/os/Parcel:recycle	()V
        //   115: aload 4
        //   117: athrow
        // Local variable table:
        //   start	length	slot	name	signature
        //   0	118	0	this	zza
        //   0	118	1	paramLong	long
        //   0	118	3	paramBoolean	boolean
        //   0	118	4	paramPendingIntent	PendingIntent
        //   1	89	5	i	int
        //   6	105	6	localParcel1	Parcel
        //   11	95	7	localParcel2	Parcel
        // Exception table:
        //   from	to	target	type
        //   13	26	103	finally
        //   30	37	103	finally
        //   42	56	103	finally
        //   56	77	103	finally
        //   94	100	103	finally
      }
      
      public void zza(PendingIntent paramPendingIntent, zzzp paramzzzp)
        throws RemoteException
      {
        Parcel localParcel1 = Parcel.obtain();
        Parcel localParcel2 = Parcel.obtain();
        for (;;)
        {
          try
          {
            localParcel1.writeInterfaceToken("com.google.android.gms.location.internal.IGoogleLocationManagerService");
            if (paramPendingIntent != null)
            {
              localParcel1.writeInt(1);
              paramPendingIntent.writeToParcel(localParcel1, 0);
              if (paramzzzp != null)
              {
                paramPendingIntent = paramzzzp.asBinder();
                localParcel1.writeStrongBinder(paramPendingIntent);
                this.zzrj.transact(73, localParcel1, localParcel2, 0);
                localParcel2.readException();
              }
            }
            else
            {
              localParcel1.writeInt(0);
              continue;
            }
            paramPendingIntent = null;
          }
          finally
          {
            localParcel2.recycle();
            localParcel1.recycle();
          }
        }
      }
      
      public void zza(PendingIntent paramPendingIntent, zzj paramzzj, String paramString)
        throws RemoteException
      {
        Parcel localParcel1 = Parcel.obtain();
        Parcel localParcel2 = Parcel.obtain();
        for (;;)
        {
          try
          {
            localParcel1.writeInterfaceToken("com.google.android.gms.location.internal.IGoogleLocationManagerService");
            if (paramPendingIntent != null)
            {
              localParcel1.writeInt(1);
              paramPendingIntent.writeToParcel(localParcel1, 0);
              if (paramzzj != null)
              {
                paramPendingIntent = paramzzj.asBinder();
                localParcel1.writeStrongBinder(paramPendingIntent);
                localParcel1.writeString(paramString);
                this.zzrj.transact(2, localParcel1, localParcel2, 0);
                localParcel2.readException();
              }
            }
            else
            {
              localParcel1.writeInt(0);
              continue;
            }
            paramPendingIntent = null;
          }
          finally
          {
            localParcel2.recycle();
            localParcel1.recycle();
          }
        }
      }
      
      /* Error */
      public void zza(Location paramLocation, int paramInt)
        throws RemoteException
      {
        // Byte code:
        //   0: invokestatic 31	android/os/Parcel:obtain	()Landroid/os/Parcel;
        //   3: astore_3
        //   4: invokestatic 31	android/os/Parcel:obtain	()Landroid/os/Parcel;
        //   7: astore 4
        //   9: aload_3
        //   10: ldc 33
        //   12: invokevirtual 37	android/os/Parcel:writeInterfaceToken	(Ljava/lang/String;)V
        //   15: aload_1
        //   16: ifnull +50 -> 66
        //   19: aload_3
        //   20: iconst_1
        //   21: invokevirtual 75	android/os/Parcel:writeInt	(I)V
        //   24: aload_1
        //   25: aload_3
        //   26: iconst_0
        //   27: invokevirtual 98	android/location/Location:writeToParcel	(Landroid/os/Parcel;I)V
        //   30: aload_3
        //   31: iload_2
        //   32: invokevirtual 75	android/os/Parcel:writeInt	(I)V
        //   35: aload_0
        //   36: getfield 18	com/google/android/gms/location/internal/zzk$zza$zza:zzrj	Landroid/os/IBinder;
        //   39: bipush 26
        //   41: aload_3
        //   42: aload 4
        //   44: iconst_0
        //   45: invokeinterface 43 5 0
        //   50: pop
        //   51: aload 4
        //   53: invokevirtual 46	android/os/Parcel:readException	()V
        //   56: aload 4
        //   58: invokevirtual 65	android/os/Parcel:recycle	()V
        //   61: aload_3
        //   62: invokevirtual 65	android/os/Parcel:recycle	()V
        //   65: return
        //   66: aload_3
        //   67: iconst_0
        //   68: invokevirtual 75	android/os/Parcel:writeInt	(I)V
        //   71: goto -41 -> 30
        //   74: astore_1
        //   75: aload 4
        //   77: invokevirtual 65	android/os/Parcel:recycle	()V
        //   80: aload_3
        //   81: invokevirtual 65	android/os/Parcel:recycle	()V
        //   84: aload_1
        //   85: athrow
        // Local variable table:
        //   start	length	slot	name	signature
        //   0	86	0	this	zza
        //   0	86	1	paramLocation	Location
        //   0	86	2	paramInt	int
        //   3	78	3	localParcel1	Parcel
        //   7	69	4	localParcel2	Parcel
        // Exception table:
        //   from	to	target	type
        //   9	15	74	finally
        //   19	30	74	finally
        //   30	56	74	finally
        //   66	71	74	finally
      }
      
      public void zza(GeofencingRequest paramGeofencingRequest, PendingIntent paramPendingIntent, zzj paramzzj)
        throws RemoteException
      {
        Parcel localParcel1 = Parcel.obtain();
        Parcel localParcel2 = Parcel.obtain();
        for (;;)
        {
          try
          {
            localParcel1.writeInterfaceToken("com.google.android.gms.location.internal.IGoogleLocationManagerService");
            if (paramGeofencingRequest != null)
            {
              localParcel1.writeInt(1);
              paramGeofencingRequest.writeToParcel(localParcel1, 0);
              if (paramPendingIntent != null)
              {
                localParcel1.writeInt(1);
                paramPendingIntent.writeToParcel(localParcel1, 0);
                if (paramzzj == null) {
                  break label132;
                }
                paramGeofencingRequest = paramzzj.asBinder();
                localParcel1.writeStrongBinder(paramGeofencingRequest);
                this.zzrj.transact(57, localParcel1, localParcel2, 0);
                localParcel2.readException();
              }
            }
            else
            {
              localParcel1.writeInt(0);
              continue;
            }
            localParcel1.writeInt(0);
          }
          finally
          {
            localParcel2.recycle();
            localParcel1.recycle();
          }
          continue;
          label132:
          paramGeofencingRequest = null;
        }
      }
      
      public void zza(LocationRequest paramLocationRequest, PendingIntent paramPendingIntent)
        throws RemoteException
      {
        Parcel localParcel1 = Parcel.obtain();
        Parcel localParcel2 = Parcel.obtain();
        for (;;)
        {
          try
          {
            localParcel1.writeInterfaceToken("com.google.android.gms.location.internal.IGoogleLocationManagerService");
            if (paramLocationRequest != null)
            {
              localParcel1.writeInt(1);
              paramLocationRequest.writeToParcel(localParcel1, 0);
              if (paramPendingIntent != null)
              {
                localParcel1.writeInt(1);
                paramPendingIntent.writeToParcel(localParcel1, 0);
                this.zzrj.transact(9, localParcel1, localParcel2, 0);
                localParcel2.readException();
              }
            }
            else
            {
              localParcel1.writeInt(0);
              continue;
            }
            localParcel1.writeInt(0);
          }
          finally
          {
            localParcel2.recycle();
            localParcel1.recycle();
          }
        }
      }
      
      public void zza(LocationRequest paramLocationRequest, zzn paramzzn)
        throws RemoteException
      {
        Parcel localParcel1 = Parcel.obtain();
        Parcel localParcel2 = Parcel.obtain();
        for (;;)
        {
          try
          {
            localParcel1.writeInterfaceToken("com.google.android.gms.location.internal.IGoogleLocationManagerService");
            if (paramLocationRequest != null)
            {
              localParcel1.writeInt(1);
              paramLocationRequest.writeToParcel(localParcel1, 0);
              if (paramzzn != null)
              {
                paramLocationRequest = paramzzn.asBinder();
                localParcel1.writeStrongBinder(paramLocationRequest);
                this.zzrj.transact(8, localParcel1, localParcel2, 0);
                localParcel2.readException();
              }
            }
            else
            {
              localParcel1.writeInt(0);
              continue;
            }
            paramLocationRequest = null;
          }
          finally
          {
            localParcel2.recycle();
            localParcel1.recycle();
          }
        }
      }
      
      public void zza(LocationRequest paramLocationRequest, zzn paramzzn, String paramString)
        throws RemoteException
      {
        Parcel localParcel1 = Parcel.obtain();
        Parcel localParcel2 = Parcel.obtain();
        for (;;)
        {
          try
          {
            localParcel1.writeInterfaceToken("com.google.android.gms.location.internal.IGoogleLocationManagerService");
            if (paramLocationRequest != null)
            {
              localParcel1.writeInt(1);
              paramLocationRequest.writeToParcel(localParcel1, 0);
              if (paramzzn != null)
              {
                paramLocationRequest = paramzzn.asBinder();
                localParcel1.writeStrongBinder(paramLocationRequest);
                localParcel1.writeString(paramString);
                this.zzrj.transact(20, localParcel1, localParcel2, 0);
                localParcel2.readException();
              }
            }
            else
            {
              localParcel1.writeInt(0);
              continue;
            }
            paramLocationRequest = null;
          }
          finally
          {
            localParcel2.recycle();
            localParcel1.recycle();
          }
        }
      }
      
      public void zza(LocationSettingsRequest paramLocationSettingsRequest, zzl paramzzl, String paramString)
        throws RemoteException
      {
        Parcel localParcel1 = Parcel.obtain();
        Parcel localParcel2 = Parcel.obtain();
        for (;;)
        {
          try
          {
            localParcel1.writeInterfaceToken("com.google.android.gms.location.internal.IGoogleLocationManagerService");
            if (paramLocationSettingsRequest != null)
            {
              localParcel1.writeInt(1);
              paramLocationSettingsRequest.writeToParcel(localParcel1, 0);
              if (paramzzl != null)
              {
                paramLocationSettingsRequest = paramzzl.asBinder();
                localParcel1.writeStrongBinder(paramLocationSettingsRequest);
                localParcel1.writeString(paramString);
                this.zzrj.transact(63, localParcel1, localParcel2, 0);
                localParcel2.readException();
              }
            }
            else
            {
              localParcel1.writeInt(0);
              continue;
            }
            paramLocationSettingsRequest = null;
          }
          finally
          {
            localParcel2.recycle();
            localParcel1.recycle();
          }
        }
      }
      
      /* Error */
      public void zza(zzi paramzzi)
        throws RemoteException
      {
        // Byte code:
        //   0: invokestatic 31	android/os/Parcel:obtain	()Landroid/os/Parcel;
        //   3: astore_2
        //   4: invokestatic 31	android/os/Parcel:obtain	()Landroid/os/Parcel;
        //   7: astore_3
        //   8: aload_2
        //   9: ldc 33
        //   11: invokevirtual 37	android/os/Parcel:writeInterfaceToken	(Ljava/lang/String;)V
        //   14: aload_1
        //   15: ifnull +43 -> 58
        //   18: aload_1
        //   19: invokeinterface 122 1 0
        //   24: astore_1
        //   25: aload_2
        //   26: aload_1
        //   27: invokevirtual 89	android/os/Parcel:writeStrongBinder	(Landroid/os/IBinder;)V
        //   30: aload_0
        //   31: getfield 18	com/google/android/gms/location/internal/zzk$zza$zza:zzrj	Landroid/os/IBinder;
        //   34: bipush 67
        //   36: aload_2
        //   37: aload_3
        //   38: iconst_0
        //   39: invokeinterface 43 5 0
        //   44: pop
        //   45: aload_3
        //   46: invokevirtual 46	android/os/Parcel:readException	()V
        //   49: aload_3
        //   50: invokevirtual 65	android/os/Parcel:recycle	()V
        //   53: aload_2
        //   54: invokevirtual 65	android/os/Parcel:recycle	()V
        //   57: return
        //   58: aconst_null
        //   59: astore_1
        //   60: goto -35 -> 25
        //   63: astore_1
        //   64: aload_3
        //   65: invokevirtual 65	android/os/Parcel:recycle	()V
        //   68: aload_2
        //   69: invokevirtual 65	android/os/Parcel:recycle	()V
        //   72: aload_1
        //   73: athrow
        // Local variable table:
        //   start	length	slot	name	signature
        //   0	74	0	this	zza
        //   0	74	1	paramzzi	zzi
        //   3	66	2	localParcel1	Parcel
        //   7	58	3	localParcel2	Parcel
        // Exception table:
        //   from	to	target	type
        //   8	14	63	finally
        //   18	25	63	finally
        //   25	49	63	finally
      }
      
      /* Error */
      public void zza(zzj paramzzj, String paramString)
        throws RemoteException
      {
        // Byte code:
        //   0: invokestatic 31	android/os/Parcel:obtain	()Landroid/os/Parcel;
        //   3: astore_3
        //   4: invokestatic 31	android/os/Parcel:obtain	()Landroid/os/Parcel;
        //   7: astore 4
        //   9: aload_3
        //   10: ldc 33
        //   12: invokevirtual 37	android/os/Parcel:writeInterfaceToken	(Ljava/lang/String;)V
        //   15: aload_1
        //   16: ifnull +50 -> 66
        //   19: aload_1
        //   20: invokeinterface 93 1 0
        //   25: astore_1
        //   26: aload_3
        //   27: aload_1
        //   28: invokevirtual 89	android/os/Parcel:writeStrongBinder	(Landroid/os/IBinder;)V
        //   31: aload_3
        //   32: aload_2
        //   33: invokevirtual 96	android/os/Parcel:writeString	(Ljava/lang/String;)V
        //   36: aload_0
        //   37: getfield 18	com/google/android/gms/location/internal/zzk$zza$zza:zzrj	Landroid/os/IBinder;
        //   40: iconst_4
        //   41: aload_3
        //   42: aload 4
        //   44: iconst_0
        //   45: invokeinterface 43 5 0
        //   50: pop
        //   51: aload 4
        //   53: invokevirtual 46	android/os/Parcel:readException	()V
        //   56: aload 4
        //   58: invokevirtual 65	android/os/Parcel:recycle	()V
        //   61: aload_3
        //   62: invokevirtual 65	android/os/Parcel:recycle	()V
        //   65: return
        //   66: aconst_null
        //   67: astore_1
        //   68: goto -42 -> 26
        //   71: astore_1
        //   72: aload 4
        //   74: invokevirtual 65	android/os/Parcel:recycle	()V
        //   77: aload_3
        //   78: invokevirtual 65	android/os/Parcel:recycle	()V
        //   81: aload_1
        //   82: athrow
        // Local variable table:
        //   start	length	slot	name	signature
        //   0	83	0	this	zza
        //   0	83	1	paramzzj	zzj
        //   0	83	2	paramString	String
        //   3	75	3	localParcel1	Parcel
        //   7	66	4	localParcel2	Parcel
        // Exception table:
        //   from	to	target	type
        //   9	15	71	finally
        //   19	26	71	finally
        //   26	56	71	finally
      }
      
      public void zza(zzo paramzzo, PendingIntent paramPendingIntent)
        throws RemoteException
      {
        Parcel localParcel1 = Parcel.obtain();
        Parcel localParcel2 = Parcel.obtain();
        for (;;)
        {
          try
          {
            localParcel1.writeInterfaceToken("com.google.android.gms.location.internal.IGoogleLocationManagerService");
            if (paramzzo != null)
            {
              localParcel1.writeInt(1);
              paramzzo.writeToParcel(localParcel1, 0);
              if (paramPendingIntent != null)
              {
                localParcel1.writeInt(1);
                paramPendingIntent.writeToParcel(localParcel1, 0);
                this.zzrj.transact(53, localParcel1, localParcel2, 0);
                localParcel2.readException();
              }
            }
            else
            {
              localParcel1.writeInt(0);
              continue;
            }
            localParcel1.writeInt(0);
          }
          finally
          {
            localParcel2.recycle();
            localParcel1.recycle();
          }
        }
      }
      
      public void zza(zzo paramzzo, zzn paramzzn)
        throws RemoteException
      {
        Parcel localParcel1 = Parcel.obtain();
        Parcel localParcel2 = Parcel.obtain();
        for (;;)
        {
          try
          {
            localParcel1.writeInterfaceToken("com.google.android.gms.location.internal.IGoogleLocationManagerService");
            if (paramzzo != null)
            {
              localParcel1.writeInt(1);
              paramzzo.writeToParcel(localParcel1, 0);
              if (paramzzn != null)
              {
                paramzzo = paramzzn.asBinder();
                localParcel1.writeStrongBinder(paramzzo);
                this.zzrj.transact(52, localParcel1, localParcel2, 0);
                localParcel2.readException();
              }
            }
            else
            {
              localParcel1.writeInt(0);
              continue;
            }
            paramzzo = null;
          }
          finally
          {
            localParcel2.recycle();
            localParcel1.recycle();
          }
        }
      }
      
      /* Error */
      public void zza(zzq paramzzq)
        throws RemoteException
      {
        // Byte code:
        //   0: invokestatic 31	android/os/Parcel:obtain	()Landroid/os/Parcel;
        //   3: astore_2
        //   4: invokestatic 31	android/os/Parcel:obtain	()Landroid/os/Parcel;
        //   7: astore_3
        //   8: aload_2
        //   9: ldc 33
        //   11: invokevirtual 37	android/os/Parcel:writeInterfaceToken	(Ljava/lang/String;)V
        //   14: aload_1
        //   15: ifnull +42 -> 57
        //   18: aload_2
        //   19: iconst_1
        //   20: invokevirtual 75	android/os/Parcel:writeInt	(I)V
        //   23: aload_1
        //   24: aload_2
        //   25: iconst_0
        //   26: invokevirtual 132	com/google/android/gms/location/internal/zzq:writeToParcel	(Landroid/os/Parcel;I)V
        //   29: aload_0
        //   30: getfield 18	com/google/android/gms/location/internal/zzk$zza$zza:zzrj	Landroid/os/IBinder;
        //   33: bipush 59
        //   35: aload_2
        //   36: aload_3
        //   37: iconst_0
        //   38: invokeinterface 43 5 0
        //   43: pop
        //   44: aload_3
        //   45: invokevirtual 46	android/os/Parcel:readException	()V
        //   48: aload_3
        //   49: invokevirtual 65	android/os/Parcel:recycle	()V
        //   52: aload_2
        //   53: invokevirtual 65	android/os/Parcel:recycle	()V
        //   56: return
        //   57: aload_2
        //   58: iconst_0
        //   59: invokevirtual 75	android/os/Parcel:writeInt	(I)V
        //   62: goto -33 -> 29
        //   65: astore_1
        //   66: aload_3
        //   67: invokevirtual 65	android/os/Parcel:recycle	()V
        //   70: aload_2
        //   71: invokevirtual 65	android/os/Parcel:recycle	()V
        //   74: aload_1
        //   75: athrow
        // Local variable table:
        //   start	length	slot	name	signature
        //   0	76	0	this	zza
        //   0	76	1	paramzzq	zzq
        //   3	68	2	localParcel1	Parcel
        //   7	60	3	localParcel2	Parcel
        // Exception table:
        //   from	to	target	type
        //   8	14	65	finally
        //   18	29	65	finally
        //   29	48	65	finally
        //   57	62	65	finally
      }
      
      public void zza(zza paramzza, PendingIntent paramPendingIntent, zzzp paramzzzp)
        throws RemoteException
      {
        Parcel localParcel1 = Parcel.obtain();
        Parcel localParcel2 = Parcel.obtain();
        for (;;)
        {
          try
          {
            localParcel1.writeInterfaceToken("com.google.android.gms.location.internal.IGoogleLocationManagerService");
            if (paramzza != null)
            {
              localParcel1.writeInt(1);
              paramzza.writeToParcel(localParcel1, 0);
              if (paramPendingIntent != null)
              {
                localParcel1.writeInt(1);
                paramPendingIntent.writeToParcel(localParcel1, 0);
                if (paramzzzp == null) {
                  break label132;
                }
                paramzza = paramzzzp.asBinder();
                localParcel1.writeStrongBinder(paramzza);
                this.zzrj.transact(70, localParcel1, localParcel2, 0);
                localParcel2.readException();
              }
            }
            else
            {
              localParcel1.writeInt(0);
              continue;
            }
            localParcel1.writeInt(0);
          }
          finally
          {
            localParcel2.recycle();
            localParcel1.recycle();
          }
          continue;
          label132:
          paramzza = null;
        }
      }
      
      public void zza(zzf paramzzf, PendingIntent paramPendingIntent, zzzp paramzzzp)
        throws RemoteException
      {
        Parcel localParcel1 = Parcel.obtain();
        Parcel localParcel2 = Parcel.obtain();
        for (;;)
        {
          try
          {
            localParcel1.writeInterfaceToken("com.google.android.gms.location.internal.IGoogleLocationManagerService");
            if (paramzzf != null)
            {
              localParcel1.writeInt(1);
              paramzzf.writeToParcel(localParcel1, 0);
              if (paramPendingIntent != null)
              {
                localParcel1.writeInt(1);
                paramPendingIntent.writeToParcel(localParcel1, 0);
                if (paramzzzp == null) {
                  break label132;
                }
                paramzzf = paramzzzp.asBinder();
                localParcel1.writeStrongBinder(paramzzf);
                this.zzrj.transact(72, localParcel1, localParcel2, 0);
                localParcel2.readException();
              }
            }
            else
            {
              localParcel1.writeInt(0);
              continue;
            }
            localParcel1.writeInt(0);
          }
          finally
          {
            localParcel2.recycle();
            localParcel1.recycle();
          }
          continue;
          label132:
          paramzzf = null;
        }
      }
      
      /* Error */
      public void zza(zzn paramzzn)
        throws RemoteException
      {
        // Byte code:
        //   0: invokestatic 31	android/os/Parcel:obtain	()Landroid/os/Parcel;
        //   3: astore_2
        //   4: invokestatic 31	android/os/Parcel:obtain	()Landroid/os/Parcel;
        //   7: astore_3
        //   8: aload_2
        //   9: ldc 33
        //   11: invokevirtual 37	android/os/Parcel:writeInterfaceToken	(Ljava/lang/String;)V
        //   14: aload_1
        //   15: ifnull +43 -> 58
        //   18: aload_1
        //   19: invokeinterface 110 1 0
        //   24: astore_1
        //   25: aload_2
        //   26: aload_1
        //   27: invokevirtual 89	android/os/Parcel:writeStrongBinder	(Landroid/os/IBinder;)V
        //   30: aload_0
        //   31: getfield 18	com/google/android/gms/location/internal/zzk$zza$zza:zzrj	Landroid/os/IBinder;
        //   34: bipush 10
        //   36: aload_2
        //   37: aload_3
        //   38: iconst_0
        //   39: invokeinterface 43 5 0
        //   44: pop
        //   45: aload_3
        //   46: invokevirtual 46	android/os/Parcel:readException	()V
        //   49: aload_3
        //   50: invokevirtual 65	android/os/Parcel:recycle	()V
        //   53: aload_2
        //   54: invokevirtual 65	android/os/Parcel:recycle	()V
        //   57: return
        //   58: aconst_null
        //   59: astore_1
        //   60: goto -35 -> 25
        //   63: astore_1
        //   64: aload_3
        //   65: invokevirtual 65	android/os/Parcel:recycle	()V
        //   68: aload_2
        //   69: invokevirtual 65	android/os/Parcel:recycle	()V
        //   72: aload_1
        //   73: athrow
        // Local variable table:
        //   start	length	slot	name	signature
        //   0	74	0	this	zza
        //   0	74	1	paramzzn	zzn
        //   3	66	2	localParcel1	Parcel
        //   7	58	3	localParcel2	Parcel
        // Exception table:
        //   from	to	target	type
        //   8	14	63	finally
        //   18	25	63	finally
        //   25	49	63	finally
      }
      
      public void zza(zzv paramzzv, zzj paramzzj)
        throws RemoteException
      {
        Parcel localParcel1 = Parcel.obtain();
        Parcel localParcel2 = Parcel.obtain();
        for (;;)
        {
          try
          {
            localParcel1.writeInterfaceToken("com.google.android.gms.location.internal.IGoogleLocationManagerService");
            if (paramzzv != null)
            {
              localParcel1.writeInt(1);
              paramzzv.writeToParcel(localParcel1, 0);
              if (paramzzj != null)
              {
                paramzzv = paramzzj.asBinder();
                localParcel1.writeStrongBinder(paramzzv);
                this.zzrj.transact(74, localParcel1, localParcel2, 0);
                localParcel2.readException();
              }
            }
            else
            {
              localParcel1.writeInt(0);
              continue;
            }
            paramzzv = null;
          }
          finally
          {
            localParcel2.recycle();
            localParcel1.recycle();
          }
        }
      }
      
      public void zza(List<zzt> paramList, PendingIntent paramPendingIntent, zzj paramzzj, String paramString)
        throws RemoteException
      {
        Parcel localParcel1 = Parcel.obtain();
        Parcel localParcel2 = Parcel.obtain();
        for (;;)
        {
          try
          {
            localParcel1.writeInterfaceToken("com.google.android.gms.location.internal.IGoogleLocationManagerService");
            localParcel1.writeTypedList(paramList);
            if (paramPendingIntent != null)
            {
              localParcel1.writeInt(1);
              paramPendingIntent.writeToParcel(localParcel1, 0);
              if (paramzzj != null)
              {
                paramList = paramzzj.asBinder();
                localParcel1.writeStrongBinder(paramList);
                localParcel1.writeString(paramString);
                this.zzrj.transact(1, localParcel1, localParcel2, 0);
                localParcel2.readException();
              }
            }
            else
            {
              localParcel1.writeInt(0);
              continue;
            }
            paramList = null;
          }
          finally
          {
            localParcel2.recycle();
            localParcel1.recycle();
          }
        }
      }
      
      /* Error */
      public void zza(String[] paramArrayOfString, zzj paramzzj, String paramString)
        throws RemoteException
      {
        // Byte code:
        //   0: invokestatic 31	android/os/Parcel:obtain	()Landroid/os/Parcel;
        //   3: astore 4
        //   5: invokestatic 31	android/os/Parcel:obtain	()Landroid/os/Parcel;
        //   8: astore 5
        //   10: aload 4
        //   12: ldc 33
        //   14: invokevirtual 37	android/os/Parcel:writeInterfaceToken	(Ljava/lang/String;)V
        //   17: aload 4
        //   19: aload_1
        //   20: invokevirtual 157	android/os/Parcel:writeStringArray	([Ljava/lang/String;)V
        //   23: aload_2
        //   24: ifnull +54 -> 78
        //   27: aload_2
        //   28: invokeinterface 93 1 0
        //   33: astore_1
        //   34: aload 4
        //   36: aload_1
        //   37: invokevirtual 89	android/os/Parcel:writeStrongBinder	(Landroid/os/IBinder;)V
        //   40: aload 4
        //   42: aload_3
        //   43: invokevirtual 96	android/os/Parcel:writeString	(Ljava/lang/String;)V
        //   46: aload_0
        //   47: getfield 18	com/google/android/gms/location/internal/zzk$zza$zza:zzrj	Landroid/os/IBinder;
        //   50: iconst_3
        //   51: aload 4
        //   53: aload 5
        //   55: iconst_0
        //   56: invokeinterface 43 5 0
        //   61: pop
        //   62: aload 5
        //   64: invokevirtual 46	android/os/Parcel:readException	()V
        //   67: aload 5
        //   69: invokevirtual 65	android/os/Parcel:recycle	()V
        //   72: aload 4
        //   74: invokevirtual 65	android/os/Parcel:recycle	()V
        //   77: return
        //   78: aconst_null
        //   79: astore_1
        //   80: goto -46 -> 34
        //   83: astore_1
        //   84: aload 5
        //   86: invokevirtual 65	android/os/Parcel:recycle	()V
        //   89: aload 4
        //   91: invokevirtual 65	android/os/Parcel:recycle	()V
        //   94: aload_1
        //   95: athrow
        // Local variable table:
        //   start	length	slot	name	signature
        //   0	96	0	this	zza
        //   0	96	1	paramArrayOfString	String[]
        //   0	96	2	paramzzj	zzj
        //   0	96	3	paramString	String
        //   3	87	4	localParcel1	Parcel
        //   8	77	5	localParcel2	Parcel
        // Exception table:
        //   from	to	target	type
        //   10	23	83	finally
        //   27	34	83	finally
        //   34	67	83	finally
      }
      
      public void zzaQ(boolean paramBoolean)
        throws RemoteException
      {
        int i = 0;
        Parcel localParcel1 = Parcel.obtain();
        Parcel localParcel2 = Parcel.obtain();
        try
        {
          localParcel1.writeInterfaceToken("com.google.android.gms.location.internal.IGoogleLocationManagerService");
          if (paramBoolean) {
            i = 1;
          }
          localParcel1.writeInt(i);
          this.zzrj.transact(12, localParcel1, localParcel2, 0);
          localParcel2.readException();
          return;
        }
        finally
        {
          localParcel2.recycle();
          localParcel1.recycle();
        }
      }
      
      public void zzb(PendingIntent paramPendingIntent, zzzp paramzzzp)
        throws RemoteException
      {
        Parcel localParcel1 = Parcel.obtain();
        Parcel localParcel2 = Parcel.obtain();
        for (;;)
        {
          try
          {
            localParcel1.writeInterfaceToken("com.google.android.gms.location.internal.IGoogleLocationManagerService");
            if (paramPendingIntent != null)
            {
              localParcel1.writeInt(1);
              paramPendingIntent.writeToParcel(localParcel1, 0);
              if (paramzzzp != null)
              {
                paramPendingIntent = paramzzzp.asBinder();
                localParcel1.writeStrongBinder(paramPendingIntent);
                this.zzrj.transact(65, localParcel1, localParcel2, 0);
                localParcel2.readException();
              }
            }
            else
            {
              localParcel1.writeInt(0);
              continue;
            }
            paramPendingIntent = null;
          }
          finally
          {
            localParcel2.recycle();
            localParcel1.recycle();
          }
        }
      }
      
      /* Error */
      public void zzc(PendingIntent paramPendingIntent)
        throws RemoteException
      {
        // Byte code:
        //   0: invokestatic 31	android/os/Parcel:obtain	()Landroid/os/Parcel;
        //   3: astore_2
        //   4: invokestatic 31	android/os/Parcel:obtain	()Landroid/os/Parcel;
        //   7: astore_3
        //   8: aload_2
        //   9: ldc 33
        //   11: invokevirtual 37	android/os/Parcel:writeInterfaceToken	(Ljava/lang/String;)V
        //   14: aload_1
        //   15: ifnull +42 -> 57
        //   18: aload_2
        //   19: iconst_1
        //   20: invokevirtual 75	android/os/Parcel:writeInt	(I)V
        //   23: aload_1
        //   24: aload_2
        //   25: iconst_0
        //   26: invokevirtual 81	android/app/PendingIntent:writeToParcel	(Landroid/os/Parcel;I)V
        //   29: aload_0
        //   30: getfield 18	com/google/android/gms/location/internal/zzk$zza$zza:zzrj	Landroid/os/IBinder;
        //   33: bipush 6
        //   35: aload_2
        //   36: aload_3
        //   37: iconst_0
        //   38: invokeinterface 43 5 0
        //   43: pop
        //   44: aload_3
        //   45: invokevirtual 46	android/os/Parcel:readException	()V
        //   48: aload_3
        //   49: invokevirtual 65	android/os/Parcel:recycle	()V
        //   52: aload_2
        //   53: invokevirtual 65	android/os/Parcel:recycle	()V
        //   56: return
        //   57: aload_2
        //   58: iconst_0
        //   59: invokevirtual 75	android/os/Parcel:writeInt	(I)V
        //   62: goto -33 -> 29
        //   65: astore_1
        //   66: aload_3
        //   67: invokevirtual 65	android/os/Parcel:recycle	()V
        //   70: aload_2
        //   71: invokevirtual 65	android/os/Parcel:recycle	()V
        //   74: aload_1
        //   75: athrow
        // Local variable table:
        //   start	length	slot	name	signature
        //   0	76	0	this	zza
        //   0	76	1	paramPendingIntent	PendingIntent
        //   3	68	2	localParcel1	Parcel
        //   7	60	3	localParcel2	Parcel
        // Exception table:
        //   from	to	target	type
        //   8	14	65	finally
        //   18	29	65	finally
        //   29	48	65	finally
        //   57	62	65	finally
      }
      
      public void zzc(PendingIntent paramPendingIntent, zzzp paramzzzp)
        throws RemoteException
      {
        Parcel localParcel1 = Parcel.obtain();
        Parcel localParcel2 = Parcel.obtain();
        for (;;)
        {
          try
          {
            localParcel1.writeInterfaceToken("com.google.android.gms.location.internal.IGoogleLocationManagerService");
            if (paramPendingIntent != null)
            {
              localParcel1.writeInt(1);
              paramPendingIntent.writeToParcel(localParcel1, 0);
              if (paramzzzp != null)
              {
                paramPendingIntent = paramzzzp.asBinder();
                localParcel1.writeStrongBinder(paramPendingIntent);
                this.zzrj.transact(66, localParcel1, localParcel2, 0);
                localParcel2.readException();
              }
            }
            else
            {
              localParcel1.writeInt(0);
              continue;
            }
            paramPendingIntent = null;
          }
          finally
          {
            localParcel2.recycle();
            localParcel1.recycle();
          }
        }
      }
      
      /* Error */
      public void zzd(PendingIntent paramPendingIntent)
        throws RemoteException
      {
        // Byte code:
        //   0: invokestatic 31	android/os/Parcel:obtain	()Landroid/os/Parcel;
        //   3: astore_2
        //   4: invokestatic 31	android/os/Parcel:obtain	()Landroid/os/Parcel;
        //   7: astore_3
        //   8: aload_2
        //   9: ldc 33
        //   11: invokevirtual 37	android/os/Parcel:writeInterfaceToken	(Ljava/lang/String;)V
        //   14: aload_1
        //   15: ifnull +42 -> 57
        //   18: aload_2
        //   19: iconst_1
        //   20: invokevirtual 75	android/os/Parcel:writeInt	(I)V
        //   23: aload_1
        //   24: aload_2
        //   25: iconst_0
        //   26: invokevirtual 81	android/app/PendingIntent:writeToParcel	(Landroid/os/Parcel;I)V
        //   29: aload_0
        //   30: getfield 18	com/google/android/gms/location/internal/zzk$zza$zza:zzrj	Landroid/os/IBinder;
        //   33: bipush 11
        //   35: aload_2
        //   36: aload_3
        //   37: iconst_0
        //   38: invokeinterface 43 5 0
        //   43: pop
        //   44: aload_3
        //   45: invokevirtual 46	android/os/Parcel:readException	()V
        //   48: aload_3
        //   49: invokevirtual 65	android/os/Parcel:recycle	()V
        //   52: aload_2
        //   53: invokevirtual 65	android/os/Parcel:recycle	()V
        //   56: return
        //   57: aload_2
        //   58: iconst_0
        //   59: invokevirtual 75	android/os/Parcel:writeInt	(I)V
        //   62: goto -33 -> 29
        //   65: astore_1
        //   66: aload_3
        //   67: invokevirtual 65	android/os/Parcel:recycle	()V
        //   70: aload_2
        //   71: invokevirtual 65	android/os/Parcel:recycle	()V
        //   74: aload_1
        //   75: athrow
        // Local variable table:
        //   start	length	slot	name	signature
        //   0	76	0	this	zza
        //   0	76	1	paramPendingIntent	PendingIntent
        //   3	68	2	localParcel1	Parcel
        //   7	60	3	localParcel2	Parcel
        // Exception table:
        //   from	to	target	type
        //   8	14	65	finally
        //   18	29	65	finally
        //   29	48	65	finally
        //   57	62	65	finally
      }
      
      public void zzd(PendingIntent paramPendingIntent, zzzp paramzzzp)
        throws RemoteException
      {
        Parcel localParcel1 = Parcel.obtain();
        Parcel localParcel2 = Parcel.obtain();
        for (;;)
        {
          try
          {
            localParcel1.writeInterfaceToken("com.google.android.gms.location.internal.IGoogleLocationManagerService");
            if (paramPendingIntent != null)
            {
              localParcel1.writeInt(1);
              paramPendingIntent.writeToParcel(localParcel1, 0);
              if (paramzzzp != null)
              {
                paramPendingIntent = paramzzzp.asBinder();
                localParcel1.writeStrongBinder(paramPendingIntent);
                this.zzrj.transact(68, localParcel1, localParcel2, 0);
                localParcel2.readException();
              }
            }
            else
            {
              localParcel1.writeInt(0);
              continue;
            }
            paramPendingIntent = null;
          }
          finally
          {
            localParcel2.recycle();
            localParcel1.recycle();
          }
        }
      }
      
      /* Error */
      public void zzd(Location paramLocation)
        throws RemoteException
      {
        // Byte code:
        //   0: invokestatic 31	android/os/Parcel:obtain	()Landroid/os/Parcel;
        //   3: astore_2
        //   4: invokestatic 31	android/os/Parcel:obtain	()Landroid/os/Parcel;
        //   7: astore_3
        //   8: aload_2
        //   9: ldc 33
        //   11: invokevirtual 37	android/os/Parcel:writeInterfaceToken	(Ljava/lang/String;)V
        //   14: aload_1
        //   15: ifnull +42 -> 57
        //   18: aload_2
        //   19: iconst_1
        //   20: invokevirtual 75	android/os/Parcel:writeInt	(I)V
        //   23: aload_1
        //   24: aload_2
        //   25: iconst_0
        //   26: invokevirtual 98	android/location/Location:writeToParcel	(Landroid/os/Parcel;I)V
        //   29: aload_0
        //   30: getfield 18	com/google/android/gms/location/internal/zzk$zza$zza:zzrj	Landroid/os/IBinder;
        //   33: bipush 13
        //   35: aload_2
        //   36: aload_3
        //   37: iconst_0
        //   38: invokeinterface 43 5 0
        //   43: pop
        //   44: aload_3
        //   45: invokevirtual 46	android/os/Parcel:readException	()V
        //   48: aload_3
        //   49: invokevirtual 65	android/os/Parcel:recycle	()V
        //   52: aload_2
        //   53: invokevirtual 65	android/os/Parcel:recycle	()V
        //   56: return
        //   57: aload_2
        //   58: iconst_0
        //   59: invokevirtual 75	android/os/Parcel:writeInt	(I)V
        //   62: goto -33 -> 29
        //   65: astore_1
        //   66: aload_3
        //   67: invokevirtual 65	android/os/Parcel:recycle	()V
        //   70: aload_2
        //   71: invokevirtual 65	android/os/Parcel:recycle	()V
        //   74: aload_1
        //   75: athrow
        // Local variable table:
        //   start	length	slot	name	signature
        //   0	76	0	this	zza
        //   0	76	1	paramLocation	Location
        //   3	68	2	localParcel1	Parcel
        //   7	60	3	localParcel2	Parcel
        // Exception table:
        //   from	to	target	type
        //   8	14	65	finally
        //   18	29	65	finally
        //   29	48	65	finally
        //   57	62	65	finally
      }
      
      /* Error */
      public void zzd(zzzp paramzzzp)
        throws RemoteException
      {
        // Byte code:
        //   0: invokestatic 31	android/os/Parcel:obtain	()Landroid/os/Parcel;
        //   3: astore_2
        //   4: invokestatic 31	android/os/Parcel:obtain	()Landroid/os/Parcel;
        //   7: astore_3
        //   8: aload_2
        //   9: ldc 33
        //   11: invokevirtual 37	android/os/Parcel:writeInterfaceToken	(Ljava/lang/String;)V
        //   14: aload_1
        //   15: ifnull +43 -> 58
        //   18: aload_1
        //   19: invokeinterface 86 1 0
        //   24: astore_1
        //   25: aload_2
        //   26: aload_1
        //   27: invokevirtual 89	android/os/Parcel:writeStrongBinder	(Landroid/os/IBinder;)V
        //   30: aload_0
        //   31: getfield 18	com/google/android/gms/location/internal/zzk$zza$zza:zzrj	Landroid/os/IBinder;
        //   34: bipush 71
        //   36: aload_2
        //   37: aload_3
        //   38: iconst_0
        //   39: invokeinterface 43 5 0
        //   44: pop
        //   45: aload_3
        //   46: invokevirtual 46	android/os/Parcel:readException	()V
        //   49: aload_3
        //   50: invokevirtual 65	android/os/Parcel:recycle	()V
        //   53: aload_2
        //   54: invokevirtual 65	android/os/Parcel:recycle	()V
        //   57: return
        //   58: aconst_null
        //   59: astore_1
        //   60: goto -35 -> 25
        //   63: astore_1
        //   64: aload_3
        //   65: invokevirtual 65	android/os/Parcel:recycle	()V
        //   68: aload_2
        //   69: invokevirtual 65	android/os/Parcel:recycle	()V
        //   72: aload_1
        //   73: athrow
        // Local variable table:
        //   start	length	slot	name	signature
        //   0	74	0	this	zza
        //   0	74	1	paramzzzp	zzzp
        //   3	66	2	localParcel1	Parcel
        //   7	58	3	localParcel2	Parcel
        // Exception table:
        //   from	to	target	type
        //   8	14	63	finally
        //   18	25	63	finally
        //   25	49	63	finally
      }
      
      public void zze(PendingIntent paramPendingIntent, zzzp paramzzzp)
        throws RemoteException
      {
        Parcel localParcel1 = Parcel.obtain();
        Parcel localParcel2 = Parcel.obtain();
        for (;;)
        {
          try
          {
            localParcel1.writeInterfaceToken("com.google.android.gms.location.internal.IGoogleLocationManagerService");
            if (paramPendingIntent != null)
            {
              localParcel1.writeInt(1);
              paramPendingIntent.writeToParcel(localParcel1, 0);
              if (paramzzzp != null)
              {
                paramPendingIntent = paramzzzp.asBinder();
                localParcel1.writeStrongBinder(paramPendingIntent);
                this.zzrj.transact(69, localParcel1, localParcel2, 0);
                localParcel2.readException();
              }
            }
            else
            {
              localParcel1.writeInt(0);
              continue;
            }
            paramPendingIntent = null;
          }
          finally
          {
            localParcel2.recycle();
            localParcel1.recycle();
          }
        }
      }
      
      /* Error */
      public ActivityRecognitionResult zzeR(String paramString)
        throws RemoteException
      {
        // Byte code:
        //   0: invokestatic 31	android/os/Parcel:obtain	()Landroid/os/Parcel;
        //   3: astore_2
        //   4: invokestatic 31	android/os/Parcel:obtain	()Landroid/os/Parcel;
        //   7: astore_3
        //   8: aload_2
        //   9: ldc 33
        //   11: invokevirtual 37	android/os/Parcel:writeInterfaceToken	(Ljava/lang/String;)V
        //   14: aload_2
        //   15: aload_1
        //   16: invokevirtual 96	android/os/Parcel:writeString	(Ljava/lang/String;)V
        //   19: aload_0
        //   20: getfield 18	com/google/android/gms/location/internal/zzk$zza$zza:zzrj	Landroid/os/IBinder;
        //   23: bipush 64
        //   25: aload_2
        //   26: aload_3
        //   27: iconst_0
        //   28: invokeinterface 43 5 0
        //   33: pop
        //   34: aload_3
        //   35: invokevirtual 46	android/os/Parcel:readException	()V
        //   38: aload_3
        //   39: invokevirtual 50	android/os/Parcel:readInt	()I
        //   42: ifeq +26 -> 68
        //   45: getstatic 171	com/google/android/gms/location/ActivityRecognitionResult:CREATOR	Landroid/os/Parcelable$Creator;
        //   48: aload_3
        //   49: invokeinterface 62 2 0
        //   54: checkcast 170	com/google/android/gms/location/ActivityRecognitionResult
        //   57: astore_1
        //   58: aload_3
        //   59: invokevirtual 65	android/os/Parcel:recycle	()V
        //   62: aload_2
        //   63: invokevirtual 65	android/os/Parcel:recycle	()V
        //   66: aload_1
        //   67: areturn
        //   68: aconst_null
        //   69: astore_1
        //   70: goto -12 -> 58
        //   73: astore_1
        //   74: aload_3
        //   75: invokevirtual 65	android/os/Parcel:recycle	()V
        //   78: aload_2
        //   79: invokevirtual 65	android/os/Parcel:recycle	()V
        //   82: aload_1
        //   83: athrow
        // Local variable table:
        //   start	length	slot	name	signature
        //   0	84	0	this	zza
        //   0	84	1	paramString	String
        //   3	76	2	localParcel1	Parcel
        //   7	68	3	localParcel2	Parcel
        // Exception table:
        //   from	to	target	type
        //   8	58	73	finally
      }
      
      /* Error */
      public Location zzeS(String paramString)
        throws RemoteException
      {
        // Byte code:
        //   0: invokestatic 31	android/os/Parcel:obtain	()Landroid/os/Parcel;
        //   3: astore_2
        //   4: invokestatic 31	android/os/Parcel:obtain	()Landroid/os/Parcel;
        //   7: astore_3
        //   8: aload_2
        //   9: ldc 33
        //   11: invokevirtual 37	android/os/Parcel:writeInterfaceToken	(Ljava/lang/String;)V
        //   14: aload_2
        //   15: aload_1
        //   16: invokevirtual 96	android/os/Parcel:writeString	(Ljava/lang/String;)V
        //   19: aload_0
        //   20: getfield 18	com/google/android/gms/location/internal/zzk$zza$zza:zzrj	Landroid/os/IBinder;
        //   23: bipush 21
        //   25: aload_2
        //   26: aload_3
        //   27: iconst_0
        //   28: invokeinterface 43 5 0
        //   33: pop
        //   34: aload_3
        //   35: invokevirtual 46	android/os/Parcel:readException	()V
        //   38: aload_3
        //   39: invokevirtual 50	android/os/Parcel:readInt	()I
        //   42: ifeq +26 -> 68
        //   45: getstatic 56	android/location/Location:CREATOR	Landroid/os/Parcelable$Creator;
        //   48: aload_3
        //   49: invokeinterface 62 2 0
        //   54: checkcast 52	android/location/Location
        //   57: astore_1
        //   58: aload_3
        //   59: invokevirtual 65	android/os/Parcel:recycle	()V
        //   62: aload_2
        //   63: invokevirtual 65	android/os/Parcel:recycle	()V
        //   66: aload_1
        //   67: areturn
        //   68: aconst_null
        //   69: astore_1
        //   70: goto -12 -> 58
        //   73: astore_1
        //   74: aload_3
        //   75: invokevirtual 65	android/os/Parcel:recycle	()V
        //   78: aload_2
        //   79: invokevirtual 65	android/os/Parcel:recycle	()V
        //   82: aload_1
        //   83: athrow
        // Local variable table:
        //   start	length	slot	name	signature
        //   0	84	0	this	zza
        //   0	84	1	paramString	String
        //   3	76	2	localParcel1	Parcel
        //   7	68	3	localParcel2	Parcel
        // Exception table:
        //   from	to	target	type
        //   8	58	73	finally
      }
      
      /* Error */
      public LocationAvailability zzeT(String paramString)
        throws RemoteException
      {
        // Byte code:
        //   0: invokestatic 31	android/os/Parcel:obtain	()Landroid/os/Parcel;
        //   3: astore_2
        //   4: invokestatic 31	android/os/Parcel:obtain	()Landroid/os/Parcel;
        //   7: astore_3
        //   8: aload_2
        //   9: ldc 33
        //   11: invokevirtual 37	android/os/Parcel:writeInterfaceToken	(Ljava/lang/String;)V
        //   14: aload_2
        //   15: aload_1
        //   16: invokevirtual 96	android/os/Parcel:writeString	(Ljava/lang/String;)V
        //   19: aload_0
        //   20: getfield 18	com/google/android/gms/location/internal/zzk$zza$zza:zzrj	Landroid/os/IBinder;
        //   23: bipush 34
        //   25: aload_2
        //   26: aload_3
        //   27: iconst_0
        //   28: invokeinterface 43 5 0
        //   33: pop
        //   34: aload_3
        //   35: invokevirtual 46	android/os/Parcel:readException	()V
        //   38: aload_3
        //   39: invokevirtual 50	android/os/Parcel:readInt	()I
        //   42: ifeq +26 -> 68
        //   45: getstatic 178	com/google/android/gms/location/LocationAvailability:CREATOR	Landroid/os/Parcelable$Creator;
        //   48: aload_3
        //   49: invokeinterface 62 2 0
        //   54: checkcast 177	com/google/android/gms/location/LocationAvailability
        //   57: astore_1
        //   58: aload_3
        //   59: invokevirtual 65	android/os/Parcel:recycle	()V
        //   62: aload_2
        //   63: invokevirtual 65	android/os/Parcel:recycle	()V
        //   66: aload_1
        //   67: areturn
        //   68: aconst_null
        //   69: astore_1
        //   70: goto -12 -> 58
        //   73: astore_1
        //   74: aload_3
        //   75: invokevirtual 65	android/os/Parcel:recycle	()V
        //   78: aload_2
        //   79: invokevirtual 65	android/os/Parcel:recycle	()V
        //   82: aload_1
        //   83: athrow
        // Local variable table:
        //   start	length	slot	name	signature
        //   0	84	0	this	zza
        //   0	84	1	paramString	String
        //   3	76	2	localParcel1	Parcel
        //   7	68	3	localParcel2	Parcel
        // Exception table:
        //   from	to	target	type
        //   8	58	73	finally
      }
    }
  }
}


/* Location:              /Users/tom/Downloads/dex2jar-2.0/classes.jar!/com/google/android/gms/location/internal/zzk.class
 * Java compiler version: 6 (50.0)
 * JD-Core Version:       0.7.1
 */